[{"lectures": [{"slotIndex": 7, "dayIndex": 0}, {"slotIndex": 7, "dayIndex": 3}, {"slotIndex": 7, "dayIndex": 4}], "code": "M2"}, {"lectures": [{"slotIndex": 7, "dayIndex": 0}, {"slotIndex": 7, "dayIndex": 3}, {"slotIndex": 7, "dayIndex": 4}], "code": "M2"}, {"lectures": [{"slotIndex": 7, "dayIndex": 0}, {"slotIndex": 7, "dayIndex": 3}, {"slotIndex": 7, "dayIndex": 4}], "code": "M2"}, {"lectures": [{"slotIndex": 0, "dayIndex": 0}, {"slotIndex": 0, "dayIndex": 1}, {"slotIndex": 0, "dayIndex": 2}], "code": "Es"}, {"lectures": [{"slotIndex": 0, "dayIndex": 0}, {"slotIndex": 0, "dayIndex": 1}, {"slotIndex": 0, "dayIndex": 2}], "code": "Es"}, {"lectures": [{"slotIndex": 0, "dayIndex": 0}, {"slotIndex": 0, "dayIndex": 1}, {"slotIndex": 0, "dayIndex": 2}], "code": "Es"}, {"lectures": [{"slotIndex": 4, "dayIndex": 0}, {"slotIndex": 5, "dayIndex": 0}, {"slotIndex": 4, "dayIndex": 4}, {"slotIndex": 5, "dayIndex": 4}, {"slotIndex": 4, "dayIndex": 5}, {"slotIndex": 5, "dayIndex": 5}], "code": "Fu"}, {"lectures": [{"slotIndex": 4, "dayIndex": 0}, {"slotIndex": 5, "dayIndex": 0}, {"slotIndex": 4, "dayIndex": 4}, {"slotIndex": 5, "dayIndex": 4}, {"slotIndex": 4, "dayIndex": 5}, {"slotIndex": 5, "dayIndex": 5}], "code": "Fu"}, {"lectures": [{"slotIndex": 4, "dayIndex": 0}, {"slotIndex": 5, "dayIndex": 0}, {"slotIndex": 4, "dayIndex": 4}, {"slotIndex": 5, "dayIndex": 4}, {"slotIndex": 4, "dayIndex": 5}, {"slotIndex": 5, "dayIndex": 5}], "code": "Fu"}, {"lectures": [{"slotIndex": 4, "dayIndex": 0}, {"slotIndex": 5, "dayIndex": 0}, {"slotIndex": 4, "dayIndex": 4}, {"slotIndex": 5, "dayIndex": 4}, {"slotIndex": 4, "dayIndex": 5}, {"slotIndex": 5, "dayIndex": 5}], "code": "Fu"}, {"lectures": [{"slotIndex": 4, "dayIndex": 0}, {"slotIndex": 5, "dayIndex": 0}, {"slotIndex": 4, "dayIndex": 4}, {"slotIndex": 5, "dayIndex": 4}, {"slotIndex": 4, "dayIndex": 5}, {"slotIndex": 5, "dayIndex": 5}], "code": "Fu"}, {"lectures": [{"slotIndex": 4, "dayIndex": 0}, {"slotIndex": 5, "dayIndex": 0}, {"slotIndex": 4, "dayIndex": 4}, {"slotIndex": 5, "dayIndex": 4}, {"slotIndex": 4, "dayIndex": 5}, {"slotIndex": 5, "dayIndex": 5}], "code": "Fu"}, {"lectures": [{"slotIndex": 2, "dayIndex": 2}, {"slotIndex": 3, "dayIndex": 2}, {"slotIndex": 2, "dayIndex": 3}, {"slotIndex": 3, "dayIndex": 3}, {"slotIndex": 2, "dayIndex": 4}, {"slotIndex": 3, "dayIndex": 4}], "code": "Ma"}, {"lectures": [{"slotIndex": 2, "dayIndex": 2}, {"slotIndex": 3, "dayIndex": 2}, {"slotIndex": 2, "dayIndex": 3}, {"slotIndex": 3, "dayIndex": 3}, {"slotIndex": 2, "dayIndex": 4}, {"slotIndex": 3, "dayIndex": 4}], "code": "Ma"}, {"lectures": [{"slotIndex": 2, "dayIndex": 2}, {"slotIndex": 3, "dayIndex": 2}, {"slotIndex": 2, "dayIndex": 3}, {"slotIndex": 3, "dayIndex": 3}, {"slotIndex": 2, "dayIndex": 4}, {"slotIndex": 3, "dayIndex": 4}], "code": "Ma"}, {"lectures": [{"slotIndex": 2, "dayIndex": 2}, {"slotIndex": 3, "dayIndex": 2}, {"slotIndex": 2, "dayIndex": 3}, {"slotIndex": 3, "dayIndex": 3}, {"slotIndex": 2, "dayIndex": 4}, {"slotIndex": 3, "dayIndex": 4}], "code": "Ma"}, {"lectures": [{"slotIndex": 2, "dayIndex": 2}, {"slotIndex": 3, "dayIndex": 2}, {"slotIndex": 2, "dayIndex": 3}, {"slotIndex": 3, "dayIndex": 3}, {"slotIndex": 2, "dayIndex": 4}, {"slotIndex": 3, "dayIndex": 4}], "code": "Ma"}, {"lectures": [{"slotIndex": 2, "dayIndex": 2}, {"slotIndex": 3, "dayIndex": 2}, {"slotIndex": 2, "dayIndex": 3}, {"slotIndex": 3, "dayIndex": 3}, {"slotIndex": 2, "dayIndex": 4}, {"slotIndex": 3, "dayIndex": 4}], "code": "Ma"}, {"lectures": [{"slotIndex": 5, "dayIndex": 0}, {"slotIndex": 6, "dayIndex": 0}, {"slotIndex": 5, "dayIndex": 3}, {"slotIndex": 6, "dayIndex": 3}, {"slotIndex": 5, "dayIndex": 4}, {"slotIndex": 6, "dayIndex": 4}], "code": "Et"}, {"lectures": [{"slotIndex": 5, "dayIndex": 0}, {"slotIndex": 6, "dayIndex": 0}, {"slotIndex": 5, "dayIndex": 3}, {"slotIndex": 6, "dayIndex": 3}, {"slotIndex": 5, "dayIndex": 4}, {"slotIndex": 6, "dayIndex": 4}], "code": "Et"}, {"lectures": [{"slotIndex": 5, "dayIndex": 0}, {"slotIndex": 6, "dayIndex": 0}, {"slotIndex": 5, "dayIndex": 3}, {"slotIndex": 6, "dayIndex": 3}, {"slotIndex": 5, "dayIndex": 4}, {"slotIndex": 6, "dayIndex": 4}], "code": "Et"}, {"lectures": [{"slotIndex": 5, "dayIndex": 0}, {"slotIndex": 6, "dayIndex": 0}, {"slotIndex": 5, "dayIndex": 3}, {"slotIndex": 6, "dayIndex": 3}, {"slotIndex": 5, "dayIndex": 4}, {"slotIndex": 6, "dayIndex": 4}], "code": "Et"}, {"lectures": [{"slotIndex": 5, "dayIndex": 0}, {"slotIndex": 6, "dayIndex": 0}, {"slotIndex": 5, "dayIndex": 3}, {"slotIndex": 6, "dayIndex": 3}, {"slotIndex": 5, "dayIndex": 4}, {"slotIndex": 6, "dayIndex": 4}], "code": "Et"}, {"lectures": [{"slotIndex": 5, "dayIndex": 0}, {"slotIndex": 6, "dayIndex": 0}, {"slotIndex": 5, "dayIndex": 3}, {"slotIndex": 6, "dayIndex": 3}, {"slotIndex": 5, "dayIndex": 4}, {"slotIndex": 6, "dayIndex": 4}], "code": "Et"}, {"lectures": [{"slotIndex": 5, "dayIndex": 0}, {"slotIndex": 5, "dayIndex": 3}, {"slotIndex": 5, "dayIndex": 5}], "code": "Ps"}, {"lectures": [{"slotIndex": 5, "dayIndex": 0}, {"slotIndex": 5, "dayIndex": 3}, {"slotIndex": 5, "dayIndex": 5}], "code": "Ps"}, {"lectures": [{"slotIndex": 5, "dayIndex": 0}, {"slotIndex": 5, "dayIndex": 3}, {"slotIndex": 5, "dayIndex": 5}], "code": "Ps"}, {"lectures": [{"slotIndex": 7, "dayIndex": 1}, {"slotIndex": 8, "dayIndex": 1}, {"slotIndex": 7, "dayIndex": 3}, {"slotIndex": 8, "dayIndex": 3}, {"slotIndex": 7, "dayIndex": 4}, {"slotIndex": 8, "dayIndex": 4}], "code": "Me"}, {"lectures": [{"slotIndex": 7, "dayIndex": 1}, {"slotIndex": 8, "dayIndex": 1}, {"slotIndex": 7, "dayIndex": 3}, {"slotIndex": 8, "dayIndex": 3}, {"slotIndex": 7, "dayIndex": 4}, {"slotIndex": 8, "dayIndex": 4}], "code": "Me"}, {"lectures": [{"slotIndex": 7, "dayIndex": 1}, {"slotIndex": 8, "dayIndex": 1}, {"slotIndex": 7, "dayIndex": 3}, {"slotIndex": 8, "dayIndex": 3}, {"slotIndex": 7, "dayIndex": 4}, {"slotIndex": 8, "dayIndex": 4}], "code": "Me"}, {"lectures": [{"slotIndex": 7, "dayIndex": 1}, {"slotIndex": 8, "dayIndex": 1}, {"slotIndex": 7, "dayIndex": 3}, {"slotIndex": 8, "dayIndex": 3}, {"slotIndex": 7, "dayIndex": 4}, {"slotIndex": 8, "dayIndex": 4}], "code": "Me"}, {"lectures": [{"slotIndex": 7, "dayIndex": 1}, {"slotIndex": 8, "dayIndex": 1}, {"slotIndex": 7, "dayIndex": 3}, {"slotIndex": 8, "dayIndex": 3}, {"slotIndex": 7, "dayIndex": 4}, {"slotIndex": 8, "dayIndex": 4}], "code": "Me"}, {"lectures": [{"slotIndex": 7, "dayIndex": 1}, {"slotIndex": 8, "dayIndex": 1}, {"slotIndex": 7, "dayIndex": 3}, {"slotIndex": 8, "dayIndex": 3}, {"slotIndex": 7, "dayIndex": 4}, {"slotIndex": 8, "dayIndex": 4}], "code": "Me"}, {"lectures": [{"slotIndex": 8, "dayIndex": 1}, {"slotIndex": 8, "dayIndex": 2}, {"slotIndex": 8, "dayIndex": 3}], "code": "Fr"}, {"lectures": [{"slotIndex": 8, "dayIndex": 1}, {"slotIndex": 8, "dayIndex": 2}, {"slotIndex": 8, "dayIndex": 3}], "code": "Fr"}, {"lectures": [{"slotIndex": 8, "dayIndex": 1}, {"slotIndex": 8, "dayIndex": 2}, {"slotIndex": 8, "dayIndex": 3}], "code": "Fr"}, {"lectures": [{"slotIndex": 3, "dayIndex": 1}, {"slotIndex": 4, "dayIndex": 1}, {"slotIndex": 3, "dayIndex": 3}, {"slotIndex": 4, "dayIndex": 3}, {"slotIndex": 3, "dayIndex": 4}, {"slotIndex": 4, "dayIndex": 4}], "code": "P1"}, {"lectures": [{"slotIndex": 3, "dayIndex": 1}, {"slotIndex": 4, "dayIndex": 1}, {"slotIndex": 3, "dayIndex": 3}, {"slotIndex": 4, "dayIndex": 3}, {"slotIndex": 3, "dayIndex": 4}, {"slotIndex": 4, "dayIndex": 4}], "code": "P1"}, {"lectures": [{"slotIndex": 3, "dayIndex": 1}, {"slotIndex": 4, "dayIndex": 1}, {"slotIndex": 3, "dayIndex": 3}, {"slotIndex": 4, "dayIndex": 3}, {"slotIndex": 3, "dayIndex": 4}, {"slotIndex": 4, "dayIndex": 4}], "code": "P1"}, {"lectures": [{"slotIndex": 3, "dayIndex": 1}, {"slotIndex": 4, "dayIndex": 1}, {"slotIndex": 3, "dayIndex": 3}, {"slotIndex": 4, "dayIndex": 3}, {"slotIndex": 3, "dayIndex": 4}, {"slotIndex": 4, "dayIndex": 4}], "code": "P1"}, {"lectures": [{"slotIndex": 3, "dayIndex": 1}, {"slotIndex": 4, "dayIndex": 1}, {"slotIndex": 3, "dayIndex": 3}, {"slotIndex": 4, "dayIndex": 3}, {"slotIndex": 3, "dayIndex": 4}, {"slotIndex": 4, "dayIndex": 4}], "code": "P1"}, {"lectures": [{"slotIndex": 3, "dayIndex": 1}, {"slotIndex": 4, "dayIndex": 1}, {"slotIndex": 3, "dayIndex": 3}, {"slotIndex": 4, "dayIndex": 3}, {"slotIndex": 3, "dayIndex": 4}, {"slotIndex": 4, "dayIndex": 4}], "code": "P1"}, {"lectures": [{"slotIndex": 7, "dayIndex": 0}, {"slotIndex": 7, "dayIndex": 1}, {"slotIndex": 7, "dayIndex": 2}], "code": "Ad"}, {"lectures": [{"slotIndex": 7, "dayIndex": 0}, {"slotIndex": 7, "dayIndex": 1}, {"slotIndex": 7, "dayIndex": 2}], "code": "Ad"}, {"lectures": [{"slotIndex": 7, "dayIndex": 0}, {"slotIndex": 7, "dayIndex": 1}, {"slotIndex": 7, "dayIndex": 2}], "code": "Ad"}, {"lectures": [{"slotIndex": 4, "dayIndex": 0}, {"slotIndex": 5, "dayIndex": 0}, {"slotIndex": 4, "dayIndex": 1}, {"slotIndex": 5, "dayIndex": 1}, {"slotIndex": 4, "dayIndex": 4}, {"slotIndex": 5, "dayIndex": 4}], "code": "Am"}, {"lectures": [{"slotIndex": 4, "dayIndex": 0}, {"slotIndex": 5, "dayIndex": 0}, {"slotIndex": 4, "dayIndex": 1}, {"slotIndex": 5, "dayIndex": 1}, {"slotIndex": 4, "dayIndex": 4}, {"slotIndex": 5, "dayIndex": 4}], "code": "Am"}, {"lectures": [{"slotIndex": 4, "dayIndex": 0}, {"slotIndex": 5, "dayIndex": 0}, {"slotIndex": 4, "dayIndex": 1}, {"slotIndex": 5, "dayIndex": 1}, {"slotIndex": 4, "dayIndex": 4}, {"slotIndex": 5, "dayIndex": 4}], "code": "Am"}, {"lectures": [{"slotIndex": 4, "dayIndex": 0}, {"slotIndex": 5, "dayIndex": 0}, {"slotIndex": 4, "dayIndex": 1}, {"slotIndex": 5, "dayIndex": 1}, {"slotIndex": 4, "dayIndex": 4}, {"slotIndex": 5, "dayIndex": 4}], "code": "Am"}, {"lectures": [{"slotIndex": 4, "dayIndex": 0}, {"slotIndex": 5, "dayIndex": 0}, {"slotIndex": 4, "dayIndex": 1}, {"slotIndex": 5, "dayIndex": 1}, {"slotIndex": 4, "dayIndex": 4}, {"slotIndex": 5, "dayIndex": 4}], "code": "Am"}, {"lectures": [{"slotIndex": 4, "dayIndex": 0}, {"slotIndex": 5, "dayIndex": 0}, {"slotIndex": 4, "dayIndex": 1}, {"slotIndex": 5, "dayIndex": 1}, {"slotIndex": 4, "dayIndex": 4}, {"slotIndex": 5, "dayIndex": 4}], "code": "Am"}, {"lectures": [{"slotIndex": 1, "dayIndex": 0}, {"slotIndex": 1, "dayIndex": 1}, {"slotIndex": 1, "dayIndex": 2}], "code": "Bi"}, {"lectures": [{"slotIndex": 1, "dayIndex": 0}, {"slotIndex": 1, "dayIndex": 1}, {"slotIndex": 1, "dayIndex": 2}], "code": "Bi"}, {"lectures": [{"slotIndex": 1, "dayIndex": 0}, {"slotIndex": 1, "dayIndex": 1}, {"slotIndex": 1, "dayIndex": 2}], "code": "Bi"}, {"lectures": [{"slotIndex": 0, "dayIndex": 0}, {"slotIndex": 0, "dayIndex": 2}, {"slotIndex": 0, "dayIndex": 4}], "code": "Bs"}, {"lectures": [{"slotIndex": 0, "dayIndex": 0}, {"slotIndex": 0, "dayIndex": 2}, {"slotIndex": 0, "dayIndex": 4}], "code": "Bs"}, {"lectures": [{"slotIndex": 0, "dayIndex": 0}, {"slotIndex": 0, "dayIndex": 2}, {"slotIndex": 0, "dayIndex": 4}], "code": "Bs"}, {"lectures": [{"slotIndex": 3, "dayIndex": 1}, {"slotIndex": 4, "dayIndex": 1}, {"slotIndex": 3, "dayIndex": 2}, {"slotIndex": 4, "dayIndex": 2}, {"slotIndex": 3, "dayIndex": 4}, {"slotIndex": 4, "dayIndex": 4}], "code": "Pe"}, {"lectures": [{"slotIndex": 3, "dayIndex": 1}, {"slotIndex": 4, "dayIndex": 1}, {"slotIndex": 3, "dayIndex": 2}, {"slotIndex": 4, "dayIndex": 2}, {"slotIndex": 3, "dayIndex": 4}, {"slotIndex": 4, "dayIndex": 4}], "code": "Pe"}, {"lectures": [{"slotIndex": 3, "dayIndex": 1}, {"slotIndex": 4, "dayIndex": 1}, {"slotIndex": 3, "dayIndex": 2}, {"slotIndex": 4, "dayIndex": 2}, {"slotIndex": 3, "dayIndex": 4}, {"slotIndex": 4, "dayIndex": 4}], "code": "Pe"}, {"lectures": [{"slotIndex": 3, "dayIndex": 1}, {"slotIndex": 4, "dayIndex": 1}, {"slotIndex": 3, "dayIndex": 2}, {"slotIndex": 4, "dayIndex": 2}, {"slotIndex": 3, "dayIndex": 4}, {"slotIndex": 4, "dayIndex": 4}], "code": "Pe"}, {"lectures": [{"slotIndex": 3, "dayIndex": 1}, {"slotIndex": 4, "dayIndex": 1}, {"slotIndex": 3, "dayIndex": 2}, {"slotIndex": 4, "dayIndex": 2}, {"slotIndex": 3, "dayIndex": 4}, {"slotIndex": 4, "dayIndex": 4}], "code": "Pe"}, {"lectures": [{"slotIndex": 3, "dayIndex": 1}, {"slotIndex": 4, "dayIndex": 1}, {"slotIndex": 3, "dayIndex": 2}, {"slotIndex": 4, "dayIndex": 2}, {"slotIndex": 3, "dayIndex": 4}, {"slotIndex": 4, "dayIndex": 4}], "code": "Pe"}, {"lectures": [{"slotIndex": 2, "dayIndex": 0}, {"slotIndex": 3, "dayIndex": 0}, {"slotIndex": 2, "dayIndex": 1}, {"slotIndex": 3, "dayIndex": 1}, {"slotIndex": 2, "dayIndex": 2}, {"slotIndex": 3, "dayIndex": 2}], "code": "Cc"}, {"lectures": [{"slotIndex": 2, "dayIndex": 0}, {"slotIndex": 3, "dayIndex": 0}, {"slotIndex": 2, "dayIndex": 1}, {"slotIndex": 3, "dayIndex": 1}, {"slotIndex": 2, "dayIndex": 2}, {"slotIndex": 3, "dayIndex": 2}], "code": "Cc"}, {"lectures": [{"slotIndex": 2, "dayIndex": 0}, {"slotIndex": 3, "dayIndex": 0}, {"slotIndex": 2, "dayIndex": 1}, {"slotIndex": 3, "dayIndex": 1}, {"slotIndex": 2, "dayIndex": 2}, {"slotIndex": 3, "dayIndex": 2}], "code": "Cc"}, {"lectures": [{"slotIndex": 2, "dayIndex": 0}, {"slotIndex": 3, "dayIndex": 0}, {"slotIndex": 2, "dayIndex": 1}, {"slotIndex": 3, "dayIndex": 1}, {"slotIndex": 2, "dayIndex": 2}, {"slotIndex": 3, "dayIndex": 2}], "code": "Cc"}, {"lectures": [{"slotIndex": 2, "dayIndex": 0}, {"slotIndex": 3, "dayIndex": 0}, {"slotIndex": 2, "dayIndex": 1}, {"slotIndex": 3, "dayIndex": 1}, {"slotIndex": 2, "dayIndex": 2}, {"slotIndex": 3, "dayIndex": 2}], "code": "Cc"}, {"lectures": [{"slotIndex": 2, "dayIndex": 0}, {"slotIndex": 3, "dayIndex": 0}, {"slotIndex": 2, "dayIndex": 1}, {"slotIndex": 3, "dayIndex": 1}, {"slotIndex": 2, "dayIndex": 2}, {"slotIndex": 3, "dayIndex": 2}], "code": "Cc"}, {"lectures": [{"slotIndex": 3, "dayIndex": 0}, {"slotIndex": 4, "dayIndex": 0}, {"slotIndex": 3, "dayIndex": 2}, {"slotIndex": 4, "dayIndex": 2}, {"slotIndex": 3, "dayIndex": 3}, {"slotIndex": 4, "dayIndex": 3}], "code": "Ge"}, {"lectures": [{"slotIndex": 3, "dayIndex": 0}, {"slotIndex": 4, "dayIndex": 0}, {"slotIndex": 3, "dayIndex": 2}, {"slotIndex": 4, "dayIndex": 2}, {"slotIndex": 3, "dayIndex": 3}, {"slotIndex": 4, "dayIndex": 3}], "code": "Ge"}, {"lectures": [{"slotIndex": 3, "dayIndex": 0}, {"slotIndex": 4, "dayIndex": 0}, {"slotIndex": 3, "dayIndex": 2}, {"slotIndex": 4, "dayIndex": 2}, {"slotIndex": 3, "dayIndex": 3}, {"slotIndex": 4, "dayIndex": 3}], "code": "Ge"}, {"lectures": [{"slotIndex": 3, "dayIndex": 0}, {"slotIndex": 4, "dayIndex": 0}, {"slotIndex": 3, "dayIndex": 2}, {"slotIndex": 4, "dayIndex": 2}, {"slotIndex": 3, "dayIndex": 3}, {"slotIndex": 4, "dayIndex": 3}], "code": "Ge"}, {"lectures": [{"slotIndex": 3, "dayIndex": 0}, {"slotIndex": 4, "dayIndex": 0}, {"slotIndex": 3, "dayIndex": 2}, {"slotIndex": 4, "dayIndex": 2}, {"slotIndex": 3, "dayIndex": 3}, {"slotIndex": 4, "dayIndex": 3}], "code": "Ge"}, {"lectures": [{"slotIndex": 3, "dayIndex": 0}, {"slotIndex": 4, "dayIndex": 0}, {"slotIndex": 3, "dayIndex": 2}, {"slotIndex": 4, "dayIndex": 2}, {"slotIndex": 3, "dayIndex": 3}, {"slotIndex": 4, "dayIndex": 3}], "code": "Ge"}, {"lectures": [{"slotIndex": 2, "dayIndex": 0}, {"slotIndex": 3, "dayIndex": 0}, {"slotIndex": 2, "dayIndex": 2}, {"slotIndex": 3, "dayIndex": 2}, {"slotIndex": 2, "dayIndex": 3}, {"slotIndex": 3, "dayIndex": 3}], "code": "Ac"}, {"lectures": [{"slotIndex": 2, "dayIndex": 0}, {"slotIndex": 3, "dayIndex": 0}, {"slotIndex": 2, "dayIndex": 2}, {"slotIndex": 3, "dayIndex": 2}, {"slotIndex": 2, "dayIndex": 3}, {"slotIndex": 3, "dayIndex": 3}], "code": "Ac"}, {"lectures": [{"slotIndex": 2, "dayIndex": 0}, {"slotIndex": 3, "dayIndex": 0}, {"slotIndex": 2, "dayIndex": 2}, {"slotIndex": 3, "dayIndex": 2}, {"slotIndex": 2, "dayIndex": 3}, {"slotIndex": 3, "dayIndex": 3}], "code": "Ac"}, {"lectures": [{"slotIndex": 2, "dayIndex": 0}, {"slotIndex": 3, "dayIndex": 0}, {"slotIndex": 2, "dayIndex": 2}, {"slotIndex": 3, "dayIndex": 2}, {"slotIndex": 2, "dayIndex": 3}, {"slotIndex": 3, "dayIndex": 3}], "code": "Ac"}, {"lectures": [{"slotIndex": 2, "dayIndex": 0}, {"slotIndex": 3, "dayIndex": 0}, {"slotIndex": 2, "dayIndex": 2}, {"slotIndex": 3, "dayIndex": 2}, {"slotIndex": 2, "dayIndex": 3}, {"slotIndex": 3, "dayIndex": 3}], "code": "Ac"}, {"lectures": [{"slotIndex": 2, "dayIndex": 0}, {"slotIndex": 3, "dayIndex": 0}, {"slotIndex": 2, "dayIndex": 2}, {"slotIndex": 3, "dayIndex": 2}, {"slotIndex": 2, "dayIndex": 3}, {"slotIndex": 3, "dayIndex": 3}], "code": "Ac"}, {"lectures": [{"slotIndex": 7, "dayIndex": 0}, {"slotIndex": 7, "dayIndex": 3}, {"slotIndex": 7, "dayIndex": 4}], "code": "Ch"}, {"lectures": [{"slotIndex": 7, "dayIndex": 0}, {"slotIndex": 7, "dayIndex": 3}, {"slotIndex": 7, "dayIndex": 4}], "code": "Ch"}, {"lectures": [{"slotIndex": 7, "dayIndex": 0}, {"slotIndex": 7, "dayIndex": 3}, {"slotIndex": 7, "dayIndex": 4}], "code": "Ch"}, {"lectures": [{"slotIndex": 6, "dayIndex": 1}, {"slotIndex": 7, "dayIndex": 1}, {"slotIndex": 6, "dayIndex": 2}, {"slotIndex": 7, "dayIndex": 2}, {"slotIndex": 6, "dayIndex": 5}, {"slotIndex": 7, "dayIndex": 5}], "code": "Sw"}, {"lectures": [{"slotIndex": 6, "dayIndex": 1}, {"slotIndex": 7, "dayIndex": 1}, {"slotIndex": 6, "dayIndex": 2}, {"slotIndex": 7, "dayIndex": 2}, {"slotIndex": 6, "dayIndex": 5}, {"slotIndex": 7, "dayIndex": 5}], "code": "Sw"}, {"lectures": [{"slotIndex": 6, "dayIndex": 1}, {"slotIndex": 7, "dayIndex": 1}, {"slotIndex": 6, "dayIndex": 2}, {"slotIndex": 7, "dayIndex": 2}, {"slotIndex": 6, "dayIndex": 5}, {"slotIndex": 7, "dayIndex": 5}], "code": "Sw"}, {"lectures": [{"slotIndex": 6, "dayIndex": 1}, {"slotIndex": 7, "dayIndex": 1}, {"slotIndex": 6, "dayIndex": 2}, {"slotIndex": 7, "dayIndex": 2}, {"slotIndex": 6, "dayIndex": 5}, {"slotIndex": 7, "dayIndex": 5}], "code": "Sw"}, {"lectures": [{"slotIndex": 6, "dayIndex": 1}, {"slotIndex": 7, "dayIndex": 1}, {"slotIndex": 6, "dayIndex": 2}, {"slotIndex": 7, "dayIndex": 2}, {"slotIndex": 6, "dayIndex": 5}, {"slotIndex": 7, "dayIndex": 5}], "code": "Sw"}, {"lectures": [{"slotIndex": 6, "dayIndex": 1}, {"slotIndex": 7, "dayIndex": 1}, {"slotIndex": 6, "dayIndex": 2}, {"slotIndex": 7, "dayIndex": 2}, {"slotIndex": 6, "dayIndex": 5}, {"slotIndex": 7, "dayIndex": 5}], "code": "Sw"}, {"lectures": [{"slotIndex": 1, "dayIndex": 0}, {"slotIndex": 2, "dayIndex": 0}, {"slotIndex": 1, "dayIndex": 1}, {"slotIndex": 2, "dayIndex": 1}, {"slotIndex": 1, "dayIndex": 5}, {"slotIndex": 2, "dayIndex": 5}], "code": "He"}, {"lectures": [{"slotIndex": 1, "dayIndex": 0}, {"slotIndex": 2, "dayIndex": 0}, {"slotIndex": 1, "dayIndex": 1}, {"slotIndex": 2, "dayIndex": 1}, {"slotIndex": 1, "dayIndex": 5}, {"slotIndex": 2, "dayIndex": 5}], "code": "He"}, {"lectures": [{"slotIndex": 1, "dayIndex": 0}, {"slotIndex": 2, "dayIndex": 0}, {"slotIndex": 1, "dayIndex": 1}, {"slotIndex": 2, "dayIndex": 1}, {"slotIndex": 1, "dayIndex": 5}, {"slotIndex": 2, "dayIndex": 5}], "code": "He"}, {"lectures": [{"slotIndex": 1, "dayIndex": 0}, {"slotIndex": 2, "dayIndex": 0}, {"slotIndex": 1, "dayIndex": 1}, {"slotIndex": 2, "dayIndex": 1}, {"slotIndex": 1, "dayIndex": 5}, {"slotIndex": 2, "dayIndex": 5}], "code": "He"}, {"lectures": [{"slotIndex": 1, "dayIndex": 0}, {"slotIndex": 2, "dayIndex": 0}, {"slotIndex": 1, "dayIndex": 1}, {"slotIndex": 2, "dayIndex": 1}, {"slotIndex": 1, "dayIndex": 5}, {"slotIndex": 2, "dayIndex": 5}], "code": "He"}, {"lectures": [{"slotIndex": 1, "dayIndex": 0}, {"slotIndex": 2, "dayIndex": 0}, {"slotIndex": 1, "dayIndex": 1}, {"slotIndex": 2, "dayIndex": 1}, {"slotIndex": 1, "dayIndex": 5}, {"slotIndex": 2, "dayIndex": 5}], "code": "He"}, {"lectures": [{"slotIndex": 2, "dayIndex": 0}, {"slotIndex": 3, "dayIndex": 0}, {"slotIndex": 2, "dayIndex": 2}, {"slotIndex": 3, "dayIndex": 2}, {"slotIndex": 2, "dayIndex": 4}, {"slotIndex": 3, "dayIndex": 4}], "code": "Sp"}, {"lectures": [{"slotIndex": 2, "dayIndex": 0}, {"slotIndex": 3, "dayIndex": 0}, {"slotIndex": 2, "dayIndex": 2}, {"slotIndex": 3, "dayIndex": 2}, {"slotIndex": 2, "dayIndex": 4}, {"slotIndex": 3, "dayIndex": 4}], "code": "Sp"}, {"lectures": [{"slotIndex": 2, "dayIndex": 0}, {"slotIndex": 3, "dayIndex": 0}, {"slotIndex": 2, "dayIndex": 2}, {"slotIndex": 3, "dayIndex": 2}, {"slotIndex": 2, "dayIndex": 4}, {"slotIndex": 3, "dayIndex": 4}], "code": "Sp"}, {"lectures": [{"slotIndex": 2, "dayIndex": 0}, {"slotIndex": 3, "dayIndex": 0}, {"slotIndex": 2, "dayIndex": 2}, {"slotIndex": 3, "dayIndex": 2}, {"slotIndex": 2, "dayIndex": 4}, {"slotIndex": 3, "dayIndex": 4}], "code": "Sp"}, {"lectures": [{"slotIndex": 2, "dayIndex": 0}, {"slotIndex": 3, "dayIndex": 0}, {"slotIndex": 2, "dayIndex": 2}, {"slotIndex": 3, "dayIndex": 2}, {"slotIndex": 2, "dayIndex": 4}, {"slotIndex": 3, "dayIndex": 4}], "code": "Sp"}, {"lectures": [{"slotIndex": 2, "dayIndex": 0}, {"slotIndex": 3, "dayIndex": 0}, {"slotIndex": 2, "dayIndex": 2}, {"slotIndex": 3, "dayIndex": 2}, {"slotIndex": 2, "dayIndex": 4}, {"slotIndex": 3, "dayIndex": 4}], "code": "Sp"}, {"lectures": [{"slotIndex": 3, "dayIndex": 0}, {"slotIndex": 4, "dayIndex": 0}, {"slotIndex": 3, "dayIndex": 2}, {"slotIndex": 4, "dayIndex": 2}, {"slotIndex": 3, "dayIndex": 3}, {"slotIndex": 4, "dayIndex": 3}], "code": "Co"}, {"lectures": [{"slotIndex": 3, "dayIndex": 0}, {"slotIndex": 4, "dayIndex": 0}, {"slotIndex": 3, "dayIndex": 2}, {"slotIndex": 4, "dayIndex": 2}, {"slotIndex": 3, "dayIndex": 3}, {"slotIndex": 4, "dayIndex": 3}], "code": "Co"}, {"lectures": [{"slotIndex": 3, "dayIndex": 0}, {"slotIndex": 4, "dayIndex": 0}, {"slotIndex": 3, "dayIndex": 2}, {"slotIndex": 4, "dayIndex": 2}, {"slotIndex": 3, "dayIndex": 3}, {"slotIndex": 4, "dayIndex": 3}], "code": "Co"}, {"lectures": [{"slotIndex": 3, "dayIndex": 0}, {"slotIndex": 4, "dayIndex": 0}, {"slotIndex": 3, "dayIndex": 2}, {"slotIndex": 4, "dayIndex": 2}, {"slotIndex": 3, "dayIndex": 3}, {"slotIndex": 4, "dayIndex": 3}], "code": "Co"}, {"lectures": [{"slotIndex": 3, "dayIndex": 0}, {"slotIndex": 4, "dayIndex": 0}, {"slotIndex": 3, "dayIndex": 2}, {"slotIndex": 4, "dayIndex": 2}, {"slotIndex": 3, "dayIndex": 3}, {"slotIndex": 4, "dayIndex": 3}], "code": "Co"}, {"lectures": [{"slotIndex": 3, "dayIndex": 0}, {"slotIndex": 4, "dayIndex": 0}, {"slotIndex": 3, "dayIndex": 2}, {"slotIndex": 4, "dayIndex": 2}, {"slotIndex": 3, "dayIndex": 3}, {"slotIndex": 4, "dayIndex": 3}], "code": "Co"}, {"lectures": [{"slotIndex": 0, "dayIndex": 2}, {"slotIndex": 1, "dayIndex": 2}, {"slotIndex": 0, "dayIndex": 3}, {"slotIndex": 1, "dayIndex": 3}, {"slotIndex": 0, "dayIndex": 4}, {"slotIndex": 1, "dayIndex": 4}], "code": "Hi"}, {"lectures": [{"slotIndex": 0, "dayIndex": 2}, {"slotIndex": 1, "dayIndex": 2}, {"slotIndex": 0, "dayIndex": 3}, {"slotIndex": 1, "dayIndex": 3}, {"slotIndex": 0, "dayIndex": 4}, {"slotIndex": 1, "dayIndex": 4}], "code": "Hi"}, {"lectures": [{"slotIndex": 0, "dayIndex": 2}, {"slotIndex": 1, "dayIndex": 2}, {"slotIndex": 0, "dayIndex": 3}, {"slotIndex": 1, "dayIndex": 3}, {"slotIndex": 0, "dayIndex": 4}, {"slotIndex": 1, "dayIndex": 4}], "code": "Hi"}, {"lectures": [{"slotIndex": 0, "dayIndex": 2}, {"slotIndex": 1, "dayIndex": 2}, {"slotIndex": 0, "dayIndex": 3}, {"slotIndex": 1, "dayIndex": 3}, {"slotIndex": 0, "dayIndex": 4}, {"slotIndex": 1, "dayIndex": 4}], "code": "Hi"}, {"lectures": [{"slotIndex": 0, "dayIndex": 2}, {"slotIndex": 1, "dayIndex": 2}, {"slotIndex": 0, "dayIndex": 3}, {"slotIndex": 1, "dayIndex": 3}, {"slotIndex": 0, "dayIndex": 4}, {"slotIndex": 1, "dayIndex": 4}], "code": "Hi"}, {"lectures": [{"slotIndex": 0, "dayIndex": 2}, {"slotIndex": 1, "dayIndex": 2}, {"slotIndex": 0, "dayIndex": 3}, {"slotIndex": 1, "dayIndex": 3}, {"slotIndex": 0, "dayIndex": 4}, {"slotIndex": 1, "dayIndex": 4}], "code": "Hi"}, {"lectures": [{"slotIndex": 7, "dayIndex": 0}, {"slotIndex": 7, "dayIndex": 4}, {"slotIndex": 7, "dayIndex": 5}], "code": "S2"}, {"lectures": [{"slotIndex": 7, "dayIndex": 0}, {"slotIndex": 7, "dayIndex": 4}, {"slotIndex": 7, "dayIndex": 5}], "code": "S2"}, {"lectures": [{"slotIndex": 7, "dayIndex": 0}, {"slotIndex": 7, "dayIndex": 4}, {"slotIndex": 7, "dayIndex": 5}], "code": "S2"}, {"lectures": [{"slotIndex": 7, "dayIndex": 1}, {"slotIndex": 8, "dayIndex": 1}, {"slotIndex": 7, "dayIndex": 2}, {"slotIndex": 8, "dayIndex": 2}, {"slotIndex": 7, "dayIndex": 5}, {"slotIndex": 8, "dayIndex": 5}], "code": "Ph"}, {"lectures": [{"slotIndex": 7, "dayIndex": 1}, {"slotIndex": 8, "dayIndex": 1}, {"slotIndex": 7, "dayIndex": 2}, {"slotIndex": 8, "dayIndex": 2}, {"slotIndex": 7, "dayIndex": 5}, {"slotIndex": 8, "dayIndex": 5}], "code": "Ph"}, {"lectures": [{"slotIndex": 7, "dayIndex": 1}, {"slotIndex": 8, "dayIndex": 1}, {"slotIndex": 7, "dayIndex": 2}, {"slotIndex": 8, "dayIndex": 2}, {"slotIndex": 7, "dayIndex": 5}, {"slotIndex": 8, "dayIndex": 5}], "code": "Ph"}, {"lectures": [{"slotIndex": 7, "dayIndex": 1}, {"slotIndex": 8, "dayIndex": 1}, {"slotIndex": 7, "dayIndex": 2}, {"slotIndex": 8, "dayIndex": 2}, {"slotIndex": 7, "dayIndex": 5}, {"slotIndex": 8, "dayIndex": 5}], "code": "Ph"}, {"lectures": [{"slotIndex": 7, "dayIndex": 1}, {"slotIndex": 8, "dayIndex": 1}, {"slotIndex": 7, "dayIndex": 2}, {"slotIndex": 8, "dayIndex": 2}, {"slotIndex": 7, "dayIndex": 5}, {"slotIndex": 8, "dayIndex": 5}], "code": "Ph"}, {"lectures": [{"slotIndex": 7, "dayIndex": 1}, {"slotIndex": 8, "dayIndex": 1}, {"slotIndex": 7, "dayIndex": 2}, {"slotIndex": 8, "dayIndex": 2}, {"slotIndex": 7, "dayIndex": 5}, {"slotIndex": 8, "dayIndex": 5}], "code": "Ph"}, {"lectures": [{"slotIndex": 6, "dayIndex": 0}, {"slotIndex": 7, "dayIndex": 0}, {"slotIndex": 6, "dayIndex": 4}, {"slotIndex": 7, "dayIndex": 4}, {"slotIndex": 6, "dayIndex": 5}, {"slotIndex": 7, "dayIndex": 5}], "code": "Mu"}, {"lectures": [{"slotIndex": 6, "dayIndex": 0}, {"slotIndex": 7, "dayIndex": 0}, {"slotIndex": 6, "dayIndex": 4}, {"slotIndex": 7, "dayIndex": 4}, {"slotIndex": 6, "dayIndex": 5}, {"slotIndex": 7, "dayIndex": 5}], "code": "Mu"}, {"lectures": [{"slotIndex": 6, "dayIndex": 0}, {"slotIndex": 7, "dayIndex": 0}, {"slotIndex": 6, "dayIndex": 4}, {"slotIndex": 7, "dayIndex": 4}, {"slotIndex": 6, "dayIndex": 5}, {"slotIndex": 7, "dayIndex": 5}], "code": "Mu"}, {"lectures": [{"slotIndex": 6, "dayIndex": 0}, {"slotIndex": 7, "dayIndex": 0}, {"slotIndex": 6, "dayIndex": 4}, {"slotIndex": 7, "dayIndex": 4}, {"slotIndex": 6, "dayIndex": 5}, {"slotIndex": 7, "dayIndex": 5}], "code": "Mu"}, {"lectures": [{"slotIndex": 6, "dayIndex": 0}, {"slotIndex": 7, "dayIndex": 0}, {"slotIndex": 6, "dayIndex": 4}, {"slotIndex": 7, "dayIndex": 4}, {"slotIndex": 6, "dayIndex": 5}, {"slotIndex": 7, "dayIndex": 5}], "code": "Mu"}, {"lectures": [{"slotIndex": 6, "dayIndex": 0}, {"slotIndex": 7, "dayIndex": 0}, {"slotIndex": 6, "dayIndex": 4}, {"slotIndex": 7, "dayIndex": 4}, {"slotIndex": 6, "dayIndex": 5}, {"slotIndex": 7, "dayIndex": 5}], "code": "Mu"}, {"lectures": [{"slotIndex": 5, "dayIndex": 0}, {"slotIndex": 6, "dayIndex": 0}, {"slotIndex": 5, "dayIndex": 1}, {"slotIndex": 6, "dayIndex": 1}, {"slotIndex": 5, "dayIndex": 5}, {"slotIndex": 6, "dayIndex": 5}], "code": "It"}, {"lectures": [{"slotIndex": 5, "dayIndex": 0}, {"slotIndex": 6, "dayIndex": 0}, {"slotIndex": 5, "dayIndex": 1}, {"slotIndex": 6, "dayIndex": 1}, {"slotIndex": 5, "dayIndex": 5}, {"slotIndex": 6, "dayIndex": 5}], "code": "It"}, {"lectures": [{"slotIndex": 5, "dayIndex": 0}, {"slotIndex": 6, "dayIndex": 0}, {"slotIndex": 5, "dayIndex": 1}, {"slotIndex": 6, "dayIndex": 1}, {"slotIndex": 5, "dayIndex": 5}, {"slotIndex": 6, "dayIndex": 5}], "code": "It"}, {"lectures": [{"slotIndex": 5, "dayIndex": 0}, {"slotIndex": 6, "dayIndex": 0}, {"slotIndex": 5, "dayIndex": 1}, {"slotIndex": 6, "dayIndex": 1}, {"slotIndex": 5, "dayIndex": 5}, {"slotIndex": 6, "dayIndex": 5}], "code": "It"}, {"lectures": [{"slotIndex": 5, "dayIndex": 0}, {"slotIndex": 6, "dayIndex": 0}, {"slotIndex": 5, "dayIndex": 1}, {"slotIndex": 6, "dayIndex": 1}, {"slotIndex": 5, "dayIndex": 5}, {"slotIndex": 6, "dayIndex": 5}], "code": "It"}, {"lectures": [{"slotIndex": 5, "dayIndex": 0}, {"slotIndex": 6, "dayIndex": 0}, {"slotIndex": 5, "dayIndex": 1}, {"slotIndex": 6, "dayIndex": 1}, {"slotIndex": 5, "dayIndex": 5}, {"slotIndex": 6, "dayIndex": 5}], "code": "It"}, {"lectures": [{"slotIndex": 0, "dayIndex": 0}, {"slotIndex": 1, "dayIndex": 0}, {"slotIndex": 0, "dayIndex": 1}, {"slotIndex": 1, "dayIndex": 1}, {"slotIndex": 0, "dayIndex": 5}, {"slotIndex": 1, "dayIndex": 5}], "code": "So"}, {"lectures": [{"slotIndex": 0, "dayIndex": 0}, {"slotIndex": 1, "dayIndex": 0}, {"slotIndex": 0, "dayIndex": 1}, {"slotIndex": 1, "dayIndex": 1}, {"slotIndex": 0, "dayIndex": 5}, {"slotIndex": 1, "dayIndex": 5}], "code": "So"}, {"lectures": [{"slotIndex": 0, "dayIndex": 0}, {"slotIndex": 1, "dayIndex": 0}, {"slotIndex": 0, "dayIndex": 1}, {"slotIndex": 1, "dayIndex": 1}, {"slotIndex": 0, "dayIndex": 5}, {"slotIndex": 1, "dayIndex": 5}], "code": "So"}, {"lectures": [{"slotIndex": 0, "dayIndex": 0}, {"slotIndex": 1, "dayIndex": 0}, {"slotIndex": 0, "dayIndex": 1}, {"slotIndex": 1, "dayIndex": 1}, {"slotIndex": 0, "dayIndex": 5}, {"slotIndex": 1, "dayIndex": 5}], "code": "So"}, {"lectures": [{"slotIndex": 0, "dayIndex": 0}, {"slotIndex": 1, "dayIndex": 0}, {"slotIndex": 0, "dayIndex": 1}, {"slotIndex": 1, "dayIndex": 1}, {"slotIndex": 0, "dayIndex": 5}, {"slotIndex": 1, "dayIndex": 5}], "code": "So"}, {"lectures": [{"slotIndex": 0, "dayIndex": 0}, {"slotIndex": 1, "dayIndex": 0}, {"slotIndex": 0, "dayIndex": 1}, {"slotIndex": 1, "dayIndex": 1}, {"slotIndex": 0, "dayIndex": 5}, {"slotIndex": 1, "dayIndex": 5}], "code": "So"}, {"lectures": [{"slotIndex": 1, "dayIndex": 0}, {"slotIndex": 2, "dayIndex": 0}, {"slotIndex": 1, "dayIndex": 1}, {"slotIndex": 2, "dayIndex": 1}, {"slotIndex": 1, "dayIndex": 2}, {"slotIndex": 2, "dayIndex": 2}], "code": "Ec"}, {"lectures": [{"slotIndex": 1, "dayIndex": 0}, {"slotIndex": 2, "dayIndex": 0}, {"slotIndex": 1, "dayIndex": 1}, {"slotIndex": 2, "dayIndex": 1}, {"slotIndex": 1, "dayIndex": 2}, {"slotIndex": 2, "dayIndex": 2}], "code": "Ec"}, {"lectures": [{"slotIndex": 1, "dayIndex": 0}, {"slotIndex": 2, "dayIndex": 0}, {"slotIndex": 1, "dayIndex": 1}, {"slotIndex": 2, "dayIndex": 1}, {"slotIndex": 1, "dayIndex": 2}, {"slotIndex": 2, "dayIndex": 2}], "code": "Ec"}, {"lectures": [{"slotIndex": 1, "dayIndex": 0}, {"slotIndex": 2, "dayIndex": 0}, {"slotIndex": 1, "dayIndex": 1}, {"slotIndex": 2, "dayIndex": 1}, {"slotIndex": 1, "dayIndex": 2}, {"slotIndex": 2, "dayIndex": 2}], "code": "Ec"}, {"lectures": [{"slotIndex": 1, "dayIndex": 0}, {"slotIndex": 2, "dayIndex": 0}, {"slotIndex": 1, "dayIndex": 1}, {"slotIndex": 2, "dayIndex": 1}, {"slotIndex": 1, "dayIndex": 2}, {"slotIndex": 2, "dayIndex": 2}], "code": "Ec"}, {"lectures": [{"slotIndex": 1, "dayIndex": 0}, {"slotIndex": 2, "dayIndex": 0}, {"slotIndex": 1, "dayIndex": 1}, {"slotIndex": 2, "dayIndex": 1}, {"slotIndex": 1, "dayIndex": 2}, {"slotIndex": 2, "dayIndex": 2}], "code": "Ec"}, {"lectures": [{"slotIndex": 6, "dayIndex": 0}, {"slotIndex": 7, "dayIndex": 0}, {"slotIndex": 6, "dayIndex": 1}, {"slotIndex": 7, "dayIndex": 1}, {"slotIndex": 6, "dayIndex": 4}, {"slotIndex": 7, "dayIndex": 4}], "code": "Ls"}, {"lectures": [{"slotIndex": 6, "dayIndex": 0}, {"slotIndex": 7, "dayIndex": 0}, {"slotIndex": 6, "dayIndex": 1}, {"slotIndex": 7, "dayIndex": 1}, {"slotIndex": 6, "dayIndex": 4}, {"slotIndex": 7, "dayIndex": 4}], "code": "Ls"}, {"lectures": [{"slotIndex": 6, "dayIndex": 0}, {"slotIndex": 7, "dayIndex": 0}, {"slotIndex": 6, "dayIndex": 1}, {"slotIndex": 7, "dayIndex": 1}, {"slotIndex": 6, "dayIndex": 4}, {"slotIndex": 7, "dayIndex": 4}], "code": "Ls"}, {"lectures": [{"slotIndex": 6, "dayIndex": 0}, {"slotIndex": 7, "dayIndex": 0}, {"slotIndex": 6, "dayIndex": 1}, {"slotIndex": 7, "dayIndex": 1}, {"slotIndex": 6, "dayIndex": 4}, {"slotIndex": 7, "dayIndex": 4}], "code": "Ls"}, {"lectures": [{"slotIndex": 6, "dayIndex": 0}, {"slotIndex": 7, "dayIndex": 0}, {"slotIndex": 6, "dayIndex": 1}, {"slotIndex": 7, "dayIndex": 1}, {"slotIndex": 6, "dayIndex": 4}, {"slotIndex": 7, "dayIndex": 4}], "code": "Ls"}, {"lectures": [{"slotIndex": 6, "dayIndex": 0}, {"slotIndex": 7, "dayIndex": 0}, {"slotIndex": 6, "dayIndex": 1}, {"slotIndex": 7, "dayIndex": 1}, {"slotIndex": 6, "dayIndex": 4}, {"slotIndex": 7, "dayIndex": 4}], "code": "Ls"}, {"lectures": [{"slotIndex": 6, "dayIndex": 1}, {"slotIndex": 7, "dayIndex": 1}, {"slotIndex": 6, "dayIndex": 2}, {"slotIndex": 7, "dayIndex": 2}, {"slotIndex": 6, "dayIndex": 3}, {"slotIndex": 7, "dayIndex": 3}], "code": "P2"}, {"lectures": [{"slotIndex": 6, "dayIndex": 1}, {"slotIndex": 7, "dayIndex": 1}, {"slotIndex": 6, "dayIndex": 2}, {"slotIndex": 7, "dayIndex": 2}, {"slotIndex": 6, "dayIndex": 3}, {"slotIndex": 7, "dayIndex": 3}], "code": "P2"}, {"lectures": [{"slotIndex": 6, "dayIndex": 1}, {"slotIndex": 7, "dayIndex": 1}, {"slotIndex": 6, "dayIndex": 2}, {"slotIndex": 7, "dayIndex": 2}, {"slotIndex": 6, "dayIndex": 3}, {"slotIndex": 7, "dayIndex": 3}], "code": "P2"}, {"lectures": [{"slotIndex": 6, "dayIndex": 1}, {"slotIndex": 7, "dayIndex": 1}, {"slotIndex": 6, "dayIndex": 2}, {"slotIndex": 7, "dayIndex": 2}, {"slotIndex": 6, "dayIndex": 3}, {"slotIndex": 7, "dayIndex": 3}], "code": "P2"}, {"lectures": [{"slotIndex": 6, "dayIndex": 1}, {"slotIndex": 7, "dayIndex": 1}, {"slotIndex": 6, "dayIndex": 2}, {"slotIndex": 7, "dayIndex": 2}, {"slotIndex": 6, "dayIndex": 3}, {"slotIndex": 7, "dayIndex": 3}], "code": "P2"}, {"lectures": [{"slotIndex": 6, "dayIndex": 1}, {"slotIndex": 7, "dayIndex": 1}, {"slotIndex": 6, "dayIndex": 2}, {"slotIndex": 7, "dayIndex": 2}, {"slotIndex": 6, "dayIndex": 3}, {"slotIndex": 7, "dayIndex": 3}], "code": "P2"}, {"lectures": [{"slotIndex": 1, "dayIndex": 0}, {"slotIndex": 2, "dayIndex": 0}, {"slotIndex": 1, "dayIndex": 1}, {"slotIndex": 2, "dayIndex": 1}, {"slotIndex": 1, "dayIndex": 3}, {"slotIndex": 2, "dayIndex": 3}], "code": "El"}, {"lectures": [{"slotIndex": 1, "dayIndex": 0}, {"slotIndex": 2, "dayIndex": 0}, {"slotIndex": 1, "dayIndex": 1}, {"slotIndex": 2, "dayIndex": 1}, {"slotIndex": 1, "dayIndex": 3}, {"slotIndex": 2, "dayIndex": 3}], "code": "El"}, {"lectures": [{"slotIndex": 1, "dayIndex": 0}, {"slotIndex": 2, "dayIndex": 0}, {"slotIndex": 1, "dayIndex": 1}, {"slotIndex": 2, "dayIndex": 1}, {"slotIndex": 1, "dayIndex": 3}, {"slotIndex": 2, "dayIndex": 3}], "code": "El"}, {"lectures": [{"slotIndex": 1, "dayIndex": 0}, {"slotIndex": 2, "dayIndex": 0}, {"slotIndex": 1, "dayIndex": 1}, {"slotIndex": 2, "dayIndex": 1}, {"slotIndex": 1, "dayIndex": 3}, {"slotIndex": 2, "dayIndex": 3}], "code": "El"}, {"lectures": [{"slotIndex": 1, "dayIndex": 0}, {"slotIndex": 2, "dayIndex": 0}, {"slotIndex": 1, "dayIndex": 1}, {"slotIndex": 2, "dayIndex": 1}, {"slotIndex": 1, "dayIndex": 3}, {"slotIndex": 2, "dayIndex": 3}], "code": "El"}, {"lectures": [{"slotIndex": 1, "dayIndex": 0}, {"slotIndex": 2, "dayIndex": 0}, {"slotIndex": 1, "dayIndex": 1}, {"slotIndex": 2, "dayIndex": 1}, {"slotIndex": 1, "dayIndex": 3}, {"slotIndex": 2, "dayIndex": 3}], "code": "El"}, {"lectures": [{"slotIndex": 0, "dayIndex": 0}, {"slotIndex": 1, "dayIndex": 0}, {"slotIndex": 0, "dayIndex": 3}, {"slotIndex": 1, "dayIndex": 3}, {"slotIndex": 0, "dayIndex": 5}, {"slotIndex": 1, "dayIndex": 5}], "code": "M1"}, {"lectures": [{"slotIndex": 0, "dayIndex": 0}, {"slotIndex": 1, "dayIndex": 0}, {"slotIndex": 0, "dayIndex": 3}, {"slotIndex": 1, "dayIndex": 3}, {"slotIndex": 0, "dayIndex": 5}, {"slotIndex": 1, "dayIndex": 5}], "code": "M1"}, {"lectures": [{"slotIndex": 0, "dayIndex": 0}, {"slotIndex": 1, "dayIndex": 0}, {"slotIndex": 0, "dayIndex": 3}, {"slotIndex": 1, "dayIndex": 3}, {"slotIndex": 0, "dayIndex": 5}, {"slotIndex": 1, "dayIndex": 5}], "code": "M1"}, {"lectures": [{"slotIndex": 0, "dayIndex": 0}, {"slotIndex": 1, "dayIndex": 0}, {"slotIndex": 0, "dayIndex": 3}, {"slotIndex": 1, "dayIndex": 3}, {"slotIndex": 0, "dayIndex": 5}, {"slotIndex": 1, "dayIndex": 5}], "code": "M1"}, {"lectures": [{"slotIndex": 0, "dayIndex": 0}, {"slotIndex": 1, "dayIndex": 0}, {"slotIndex": 0, "dayIndex": 3}, {"slotIndex": 1, "dayIndex": 3}, {"slotIndex": 0, "dayIndex": 5}, {"slotIndex": 1, "dayIndex": 5}], "code": "M1"}, {"lectures": [{"slotIndex": 0, "dayIndex": 0}, {"slotIndex": 1, "dayIndex": 0}, {"slotIndex": 0, "dayIndex": 3}, {"slotIndex": 1, "dayIndex": 3}, {"slotIndex": 0, "dayIndex": 5}, {"slotIndex": 1, "dayIndex": 5}], "code": "M1"}, {"lectures": [{"slotIndex": 5, "dayIndex": 0}, {"slotIndex": 6, "dayIndex": 0}, {"slotIndex": 5, "dayIndex": 2}, {"slotIndex": 6, "dayIndex": 2}, {"slotIndex": 5, "dayIndex": 5}, {"slotIndex": 6, "dayIndex": 5}], "code": "En"}, {"lectures": [{"slotIndex": 5, "dayIndex": 0}, {"slotIndex": 6, "dayIndex": 0}, {"slotIndex": 5, "dayIndex": 2}, {"slotIndex": 6, "dayIndex": 2}, {"slotIndex": 5, "dayIndex": 5}, {"slotIndex": 6, "dayIndex": 5}], "code": "En"}, {"lectures": [{"slotIndex": 5, "dayIndex": 0}, {"slotIndex": 6, "dayIndex": 0}, {"slotIndex": 5, "dayIndex": 2}, {"slotIndex": 6, "dayIndex": 2}, {"slotIndex": 5, "dayIndex": 5}, {"slotIndex": 6, "dayIndex": 5}], "code": "En"}, {"lectures": [{"slotIndex": 5, "dayIndex": 0}, {"slotIndex": 6, "dayIndex": 0}, {"slotIndex": 5, "dayIndex": 2}, {"slotIndex": 6, "dayIndex": 2}, {"slotIndex": 5, "dayIndex": 5}, {"slotIndex": 6, "dayIndex": 5}], "code": "En"}, {"lectures": [{"slotIndex": 5, "dayIndex": 0}, {"slotIndex": 6, "dayIndex": 0}, {"slotIndex": 5, "dayIndex": 2}, {"slotIndex": 6, "dayIndex": 2}, {"slotIndex": 5, "dayIndex": 5}, {"slotIndex": 6, "dayIndex": 5}], "code": "En"}, {"lectures": [{"slotIndex": 5, "dayIndex": 0}, {"slotIndex": 6, "dayIndex": 0}, {"slotIndex": 5, "dayIndex": 2}, {"slotIndex": 6, "dayIndex": 2}, {"slotIndex": 5, "dayIndex": 5}, {"slotIndex": 6, "dayIndex": 5}], "code": "En"}, {"lectures": [{"slotIndex": 7, "dayIndex": 0}, {"slotIndex": 8, "dayIndex": 0}, {"slotIndex": 7, "dayIndex": 2}, {"slotIndex": 8, "dayIndex": 2}, {"slotIndex": 7, "dayIndex": 5}, {"slotIndex": 8, "dayIndex": 5}], "code": "Cu"}, {"lectures": [{"slotIndex": 7, "dayIndex": 0}, {"slotIndex": 8, "dayIndex": 0}, {"slotIndex": 7, "dayIndex": 2}, {"slotIndex": 8, "dayIndex": 2}, {"slotIndex": 7, "dayIndex": 5}, {"slotIndex": 8, "dayIndex": 5}], "code": "Cu"}, {"lectures": [{"slotIndex": 7, "dayIndex": 0}, {"slotIndex": 8, "dayIndex": 0}, {"slotIndex": 7, "dayIndex": 2}, {"slotIndex": 8, "dayIndex": 2}, {"slotIndex": 7, "dayIndex": 5}, {"slotIndex": 8, "dayIndex": 5}], "code": "Cu"}, {"lectures": [{"slotIndex": 7, "dayIndex": 0}, {"slotIndex": 8, "dayIndex": 0}, {"slotIndex": 7, "dayIndex": 2}, {"slotIndex": 8, "dayIndex": 2}, {"slotIndex": 7, "dayIndex": 5}, {"slotIndex": 8, "dayIndex": 5}], "code": "Cu"}, {"lectures": [{"slotIndex": 7, "dayIndex": 0}, {"slotIndex": 8, "dayIndex": 0}, {"slotIndex": 7, "dayIndex": 2}, {"slotIndex": 8, "dayIndex": 2}, {"slotIndex": 7, "dayIndex": 5}, {"slotIndex": 8, "dayIndex": 5}], "code": "Cu"}, {"lectures": [{"slotIndex": 7, "dayIndex": 0}, {"slotIndex": 8, "dayIndex": 0}, {"slotIndex": 7, "dayIndex": 2}, {"slotIndex": 8, "dayIndex": 2}, {"slotIndex": 7, "dayIndex": 5}, {"slotIndex": 8, "dayIndex": 5}], "code": "Cu"}, {"lectures": [{"slotIndex": 0, "dayIndex": 2}, {"slotIndex": 1, "dayIndex": 2}, {"slotIndex": 0, "dayIndex": 4}, {"slotIndex": 1, "dayIndex": 4}, {"slotIndex": 0, "dayIndex": 5}, {"slotIndex": 1, "dayIndex": 5}], "code": "S1"}, {"lectures": [{"slotIndex": 0, "dayIndex": 2}, {"slotIndex": 1, "dayIndex": 2}, {"slotIndex": 0, "dayIndex": 4}, {"slotIndex": 1, "dayIndex": 4}, {"slotIndex": 0, "dayIndex": 5}, {"slotIndex": 1, "dayIndex": 5}], "code": "S1"}, {"lectures": [{"slotIndex": 0, "dayIndex": 2}, {"slotIndex": 1, "dayIndex": 2}, {"slotIndex": 0, "dayIndex": 4}, {"slotIndex": 1, "dayIndex": 4}, {"slotIndex": 0, "dayIndex": 5}, {"slotIndex": 1, "dayIndex": 5}], "code": "S1"}, {"lectures": [{"slotIndex": 0, "dayIndex": 2}, {"slotIndex": 1, "dayIndex": 2}, {"slotIndex": 0, "dayIndex": 4}, {"slotIndex": 1, "dayIndex": 4}, {"slotIndex": 0, "dayIndex": 5}, {"slotIndex": 1, "dayIndex": 5}], "code": "S1"}, {"lectures": [{"slotIndex": 0, "dayIndex": 2}, {"slotIndex": 1, "dayIndex": 2}, {"slotIndex": 0, "dayIndex": 4}, {"slotIndex": 1, "dayIndex": 4}, {"slotIndex": 0, "dayIndex": 5}, {"slotIndex": 1, "dayIndex": 5}], "code": "S1"}, {"lectures": [{"slotIndex": 0, "dayIndex": 2}, {"slotIndex": 1, "dayIndex": 2}, {"slotIndex": 0, "dayIndex": 4}, {"slotIndex": 1, "dayIndex": 4}, {"slotIndex": 0, "dayIndex": 5}, {"slotIndex": 1, "dayIndex": 5}], "code": "S1"}]